gridlib/__init__.py
gridlib/calc.py
gridlib/compute.py
gridlib/data_analysis.py
gridlib/data_utils.py
gridlib/fit.py
gridlib/io/__init__.py
gridlib/io/_io_utils.py
gridlib/io/fit_results.py
gridlib/io/survival_function.py
gridlib/io/tests/__init__.py
gridlib/io/tracks.py
gridlib/plot/__init__.py
gridlib/plot/_plot_utils.py
gridlib/plot/heatmap.py
gridlib/plot/spectrum.py
gridlib/plot/survival_function.py
gridlib/resample.py
gridlib/simulate.py
gridlib-0.5.0.dist-info/LICENSE.rst
gridlib-0.5.0.dist-info/WHEEL
gridlib-0.5.0.dist-info/METADATA
gridlib-0.5.0.dist-info/RECORD
