Metadata-Version: 2.1
Name: gridlib
Version: 0.5.0
Summary: Python package to perform Genuine Rate IDentification (GRID) analysis on fluorescence survival time distributions.
Home-page: https://github.com/boydcpeters/gridlib
Keywords: gridlib
Author: Boyd Christiaan Peters
Author-email: boyd.c.peters@gmail.com
Requires-Python: >=3.7,<3.11
Classifier: Development Status :: 2 - Pre-Alpha
Classifier: Intended Audience :: Science/Research
Classifier: License :: OSI Approved :: GNU General Public License v3 (GPLv3)
Classifier: Natural Language :: English
Classifier: Programming Language :: Python :: 3
Classifier: Programming Language :: Python :: 3.7
Classifier: Programming Language :: Python :: 3.8
Classifier: Programming Language :: Python :: 3.9
Classifier: Programming Language :: Python :: 3.10
Classifier: Programming Language :: Python :: 3
Classifier: Programming Language :: Python :: 3.10
Classifier: Programming Language :: Python :: 3.7
Classifier: Programming Language :: Python :: 3.8
Classifier: Programming Language :: Python :: 3.9
Classifier: Topic :: Scientific/Engineering :: Information Analysis
Classifier: Topic :: Scientific/Engineering :: Physics
Requires-Dist: matplotlib (>=3.4.0,<4.0.0)
Requires-Dist: psutil (>=5.9.0,<6.0.0)
Requires-Dist: scipy (>=1.6.0,<2.0.0)
Requires-Dist: tqdm (>=4.63.0,<5.0.0)
Project-URL: Bug Tracker, https://github.com/boydcpeters/gridlib/issues
Project-URL: Documentation, https://gridlib.readthedocs.io/en/latest/
Project-URL: Repository, https://github.com/boydcpeters/gridlib
